setup.cfg
setup.py
colander_validators/__init__.py
colander_validators.egg-info/PKG-INFO
colander_validators.egg-info/SOURCES.txt
colander_validators.egg-info/dependency_links.txt
colander_validators.egg-info/not-zip-safe
colander_validators.egg-info/top_level.txt