Metadata-Version: 1.0
Name: colander-validators
Version: 0.0.2
Summary: Better validators for Colander based on FormEncode's validators
Home-page: http://github.com/ixmatus/colander-validators
Author: Parnell Springmeyer
Author-email: ixmatus@gmail.com
License: PSF
Platform: UNKNOWN
Classifier: Intended Audience :: Developers
Classifier: License :: OSI Approved :: Python Software Foundation License
Classifier: Programming Language :: Python
Classifier: Topic :: Software Development :: Libraries :: Python Modules
